{
  "fio version" : "fio-3.35",
  "timestamp" : 1702431268,
  "timestamp_ms" : 1702431268438,
  "time" : "Wed Dec 13 01:34:28 2023",
  "global options" : {
    "direct" : "1",
    "zonemode" : "zbd",
    "name" : "diff_bs",
    "iodepth" : "1",
    "size" : "1z",
    "filename" : "/dev/nvme0n1"
  },
  "jobs" : [
    {
      "jobname" : "zone0_write",
      "groupid" : 0,
      "error" : 0,
      "eta" : 0,
      "elapsed" : 4,
      "job options" : {
        "ioengine" : "psync",
        "bs" : "2m",
        "rw" : "write",
        "offset" : "0z"
      },
      "read" : {
        "io_bytes" : 0,
        "io_kbytes" : 0,
        "bw_bytes" : 0,
        "bw" : 0,
        "iops" : 0.000000,
        "runtime" : 0,
        "total_ios" : 0,
        "short_ios" : 0,
        "drop_ios" : 0,
        "slat_ns" : {
          "min" : 0,
          "max" : 0,
          "mean" : 0.000000,
          "stddev" : 0.000000,
          "N" : 0
        },
        "clat_ns" : {
          "min" : 0,
          "max" : 0,
          "mean" : 0.000000,
          "stddev" : 0.000000,
          "N" : 0
        },
        "lat_ns" : {
          "min" : 0,
          "max" : 0,
          "mean" : 0.000000,
          "stddev" : 0.000000,
          "N" : 0
        },
        "bw_min" : 0,
        "bw_max" : 0,
        "bw_agg" : 0.000000,
        "bw_mean" : 0.000000,
        "bw_dev" : 0.000000,
        "bw_samples" : 0,
        "iops_min" : 0,
        "iops_max" : 0,
        "iops_mean" : 0.000000,
        "iops_stddev" : 0.000000,
        "iops_samples" : 0
      },
      "write" : {
        "io_bytes" : 536870912,
        "io_kbytes" : 524288,
        "bw_bytes" : 174421998,
        "bw" : 170333,
        "iops" : 83.170890,
        "runtime" : 3078,
        "total_ios" : 256,
        "short_ios" : 0,
        "drop_ios" : 0,
        "slat_ns" : {
          "min" : 0,
          "max" : 0,
          "mean" : 0.000000,
          "stddev" : 0.000000,
          "N" : 0
        },
        "clat_ns" : {
          "min" : 4736635,
          "max" : 12356760,
          "mean" : 11974920.246094,
          "stddev" : 696689.406394,
          "N" : 256,
          "percentile" : {
            "1.000000" : 7110656,
            "5.000000" : 11993088,
            "10.000000" : 11993088,
            "20.000000" : 11993088,
            "30.000000" : 11993088,
            "40.000000" : 11993088,
            "50.000000" : 12124160,
            "60.000000" : 12124160,
            "70.000000" : 12124160,
            "80.000000" : 12124160,
            "90.000000" : 12124160,
            "95.000000" : 12124160,
            "99.000000" : 12255232,
            "99.500000" : 12255232,
            "99.900000" : 12386304,
            "99.950000" : 12386304,
            "99.990000" : 12386304
          }
        },
        "lat_ns" : {
          "min" : 4795213,
          "max" : 12414624,
          "mean" : 12018043.011719,
          "stddev" : 697408.423793,
          "N" : 256
        },
        "bw_min" : 167936,
        "bw_max" : 172032,
        "bw_agg" : 16.581738,
        "bw_mean" : 169301.333333,
        "bw_dev" : 2115.165305,
        "bw_samples" : 6,
        "iops_min" : 82,
        "iops_max" : 84,
        "iops_mean" : 82.666667,
        "iops_stddev" : 1.032796,
        "iops_samples" : 6
      },
      "trim" : {
        "io_bytes" : 0,
        "io_kbytes" : 0,
        "bw_bytes" : 0,
        "bw" : 0,
        "iops" : 0.000000,
        "runtime" : 0,
        "total_ios" : 0,
        "short_ios" : 0,
        "drop_ios" : 0,
        "slat_ns" : {
          "min" : 0,
          "max" : 0,
          "mean" : 0.000000,
          "stddev" : 0.000000,
          "N" : 0
        },
        "clat_ns" : {
          "min" : 0,
          "max" : 0,
          "mean" : 0.000000,
          "stddev" : 0.000000,
          "N" : 0
        },
        "lat_ns" : {
          "min" : 0,
          "max" : 0,
          "mean" : 0.000000,
          "stddev" : 0.000000,
          "N" : 0
        },
        "bw_min" : 0,
        "bw_max" : 0,
        "bw_agg" : 0.000000,
        "bw_mean" : 0.000000,
        "bw_dev" : 0.000000,
        "bw_samples" : 0,
        "iops_min" : 0,
        "iops_max" : 0,
        "iops_mean" : 0.000000,
        "iops_stddev" : 0.000000,
        "iops_samples" : 0
      },
      "sync" : {
        "total_ios" : 0,
        "lat_ns" : {
          "min" : 0,
          "max" : 0,
          "mean" : 0.000000,
          "stddev" : 0.000000,
          "N" : 0
        }
      },
      "job_runtime" : 3077,
      "usr_cpu" : 0.292493,
      "sys_cpu" : 0.552486,
      "ctx" : 256,
      "majf" : 0,
      "minf" : 12,
      "iodepth_level" : {
        "1" : 100.000000,
        "2" : 0.000000,
        "4" : 0.000000,
        "8" : 0.000000,
        "16" : 0.000000,
        "32" : 0.000000,
        ">=64" : 0.000000
      },
      "iodepth_submit" : {
        "0" : 0.000000,
        "4" : 100.000000,
        "8" : 0.000000,
        "16" : 0.000000,
        "32" : 0.000000,
        "64" : 0.000000,
        ">=64" : 0.000000
      },
      "iodepth_complete" : {
        "0" : 0.000000,
        "4" : 100.000000,
        "8" : 0.000000,
        "16" : 0.000000,
        "32" : 0.000000,
        "64" : 0.000000,
        ">=64" : 0.000000
      },
      "latency_ns" : {
        "2" : 0.000000,
        "4" : 0.000000,
        "10" : 0.000000,
        "20" : 0.000000,
        "50" : 0.000000,
        "100" : 0.000000,
        "250" : 0.000000,
        "500" : 0.000000,
        "750" : 0.000000,
        "1000" : 0.000000
      },
      "latency_us" : {
        "2" : 0.000000,
        "4" : 0.000000,
        "10" : 0.000000,
        "20" : 0.000000,
        "50" : 0.000000,
        "100" : 0.000000,
        "250" : 0.000000,
        "500" : 0.000000,
        "750" : 0.000000,
        "1000" : 0.000000
      },
      "latency_ms" : {
        "2" : 0.000000,
        "4" : 0.000000,
        "10" : 1.562500,
        "20" : 98.437500,
        "50" : 0.000000,
        "100" : 0.000000,
        "250" : 0.000000,
        "500" : 0.000000,
        "750" : 0.000000,
        "1000" : 0.000000,
        "2000" : 0.000000,
        ">=2000" : 0.000000
      },
      "latency_depth" : 1,
      "latency_target" : 0,
      "latency_percentile" : 100.000000,
      "latency_window" : 0
    },
    {
      "jobname" : "zone1_write",
      "groupid" : 0,
      "error" : 0,
      "eta" : 0,
      "elapsed" : 4,
      "job options" : {
        "ioengine" : "psync",
        "bs" : "2m",
        "rw" : "write",
        "offset" : "1z"
      },
      "read" : {
        "io_bytes" : 0,
        "io_kbytes" : 0,
        "bw_bytes" : 0,
        "bw" : 0,
        "iops" : 0.000000,
        "runtime" : 0,
        "total_ios" : 0,
        "short_ios" : 0,
        "drop_ios" : 0,
        "slat_ns" : {
          "min" : 0,
          "max" : 0,
          "mean" : 0.000000,
          "stddev" : 0.000000,
          "N" : 0
        },
        "clat_ns" : {
          "min" : 0,
          "max" : 0,
          "mean" : 0.000000,
          "stddev" : 0.000000,
          "N" : 0
        },
        "lat_ns" : {
          "min" : 0,
          "max" : 0,
          "mean" : 0.000000,
          "stddev" : 0.000000,
          "N" : 0
        },
        "bw_min" : 0,
        "bw_max" : 0,
        "bw_agg" : 0.000000,
        "bw_mean" : 0.000000,
        "bw_dev" : 0.000000,
        "bw_samples" : 0,
        "iops_min" : 0,
        "iops_max" : 0,
        "iops_mean" : 0.000000,
        "iops_stddev" : 0.000000,
        "iops_samples" : 0
      },
      "write" : {
        "io_bytes" : 536870912,
        "io_kbytes" : 524288,
        "bw_bytes" : 451152026,
        "bw" : 440578,
        "iops" : 215.126050,
        "runtime" : 1190,
        "total_ios" : 256,
        "short_ios" : 0,
        "drop_ios" : 0,
        "slat_ns" : {
          "min" : 0,
          "max" : 0,
          "mean" : 0.000000,
          "stddev" : 0.000000,
          "N" : 0
        },
        "clat_ns" : {
          "min" : 3378928,
          "max" : 5403193,
          "mean" : 4615506.238281,
          "stddev" : 130234.197592,
          "N" : 256,
          "percentile" : {
            "1.000000" : 3883008,
            "5.000000" : 4554752,
            "10.000000" : 4554752,
            "20.000000" : 4620288,
            "30.000000" : 4620288,
            "40.000000" : 4620288,
            "50.000000" : 4620288,
            "60.000000" : 4620288,
            "70.000000" : 4620288,
            "80.000000" : 4620288,
            "90.000000" : 4685824,
            "95.000000" : 4751360,
            "99.000000" : 4947968,
            "99.500000" : 5013504,
            "99.900000" : 5406720,
            "99.950000" : 5406720,
            "99.990000" : 5406720
          }
        },
        "lat_ns" : {
          "min" : 3391881,
          "max" : 5458540,
          "mean" : 4645856.605469,
          "stddev" : 132480.465391,
          "N" : 256
        },
        "bw_min" : 438272,
        "bw_max" : 438272,
        "bw_agg" : 42.925391,
        "bw_mean" : 438272.000000,
        "bw_dev" : 0.000000,
        "bw_samples" : 2,
        "iops_min" : 214,
        "iops_max" : 214,
        "iops_mean" : 214.000000,
        "iops_stddev" : 0.000000,
        "iops_samples" : 2
      },
      "trim" : {
        "io_bytes" : 0,
        "io_kbytes" : 0,
        "bw_bytes" : 0,
        "bw" : 0,
        "iops" : 0.000000,
        "runtime" : 0,
        "total_ios" : 0,
        "short_ios" : 0,
        "drop_ios" : 0,
        "slat_ns" : {
          "min" : 0,
          "max" : 0,
          "mean" : 0.000000,
          "stddev" : 0.000000,
          "N" : 0
        },
        "clat_ns" : {
          "min" : 0,
          "max" : 0,
          "mean" : 0.000000,
          "stddev" : 0.000000,
          "N" : 0
        },
        "lat_ns" : {
          "min" : 0,
          "max" : 0,
          "mean" : 0.000000,
          "stddev" : 0.000000,
          "N" : 0
        },
        "bw_min" : 0,
        "bw_max" : 0,
        "bw_agg" : 0.000000,
        "bw_mean" : 0.000000,
        "bw_dev" : 0.000000,
        "bw_samples" : 0,
        "iops_min" : 0,
        "iops_max" : 0,
        "iops_mean" : 0.000000,
        "iops_stddev" : 0.000000,
        "iops_samples" : 0
      },
      "sync" : {
        "total_ios" : 0,
        "lat_ns" : {
          "min" : 0,
          "max" : 0,
          "mean" : 0.000000,
          "stddev" : 0.000000,
          "N" : 0
        }
      },
      "job_runtime" : 1189,
      "usr_cpu" : 0.252313,
      "sys_cpu" : 1.429773,
      "ctx" : 256,
      "majf" : 0,
      "minf" : 11,
      "iodepth_level" : {
        "1" : 100.000000,
        "2" : 0.000000,
        "4" : 0.000000,
        "8" : 0.000000,
        "16" : 0.000000,
        "32" : 0.000000,
        ">=64" : 0.000000
      },
      "iodepth_submit" : {
        "0" : 0.000000,
        "4" : 100.000000,
        "8" : 0.000000,
        "16" : 0.000000,
        "32" : 0.000000,
        "64" : 0.000000,
        ">=64" : 0.000000
      },
      "iodepth_complete" : {
        "0" : 0.000000,
        "4" : 100.000000,
        "8" : 0.000000,
        "16" : 0.000000,
        "32" : 0.000000,
        "64" : 0.000000,
        ">=64" : 0.000000
      },
      "latency_ns" : {
        "2" : 0.000000,
        "4" : 0.000000,
        "10" : 0.000000,
        "20" : 0.000000,
        "50" : 0.000000,
        "100" : 0.000000,
        "250" : 0.000000,
        "500" : 0.000000,
        "750" : 0.000000,
        "1000" : 0.000000
      },
      "latency_us" : {
        "2" : 0.000000,
        "4" : 0.000000,
        "10" : 0.000000,
        "20" : 0.000000,
        "50" : 0.000000,
        "100" : 0.000000,
        "250" : 0.000000,
        "500" : 0.000000,
        "750" : 0.000000,
        "1000" : 0.000000
      },
      "latency_ms" : {
        "2" : 0.000000,
        "4" : 1.171875,
        "10" : 98.828125,
        "20" : 0.000000,
        "50" : 0.000000,
        "100" : 0.000000,
        "250" : 0.000000,
        "500" : 0.000000,
        "750" : 0.000000,
        "1000" : 0.000000,
        "2000" : 0.000000,
        ">=2000" : 0.000000
      },
      "latency_depth" : 1,
      "latency_target" : 0,
      "latency_percentile" : 100.000000,
      "latency_window" : 0
    },
    {
      "jobname" : "zone2_write",
      "groupid" : 0,
      "error" : 0,
      "eta" : 0,
      "elapsed" : 4,
      "job options" : {
        "ioengine" : "psync",
        "bs" : "2m",
        "rw" : "write",
        "offset" : "2z"
      },
      "read" : {
        "io_bytes" : 0,
        "io_kbytes" : 0,
        "bw_bytes" : 0,
        "bw" : 0,
        "iops" : 0.000000,
        "runtime" : 0,
        "total_ios" : 0,
        "short_ios" : 0,
        "drop_ios" : 0,
        "slat_ns" : {
          "min" : 0,
          "max" : 0,
          "mean" : 0.000000,
          "stddev" : 0.000000,
          "N" : 0
        },
        "clat_ns" : {
          "min" : 0,
          "max" : 0,
          "mean" : 0.000000,
          "stddev" : 0.000000,
          "N" : 0
        },
        "lat_ns" : {
          "min" : 0,
          "max" : 0,
          "mean" : 0.000000,
          "stddev" : 0.000000,
          "N" : 0
        },
        "bw_min" : 0,
        "bw_max" : 0,
        "bw_agg" : 0.000000,
        "bw_mean" : 0.000000,
        "bw_dev" : 0.000000,
        "bw_samples" : 0,
        "iops_min" : 0,
        "iops_max" : 0,
        "iops_mean" : 0.000000,
        "iops_stddev" : 0.000000,
        "iops_samples" : 0
      },
      "write" : {
        "io_bytes" : 536870912,
        "io_kbytes" : 524288,
        "bw_bytes" : 452673618,
        "bw" : 442064,
        "iops" : 215.851602,
        "runtime" : 1186,
        "total_ios" : 256,
        "short_ios" : 0,
        "drop_ios" : 0,
        "slat_ns" : {
          "min" : 0,
          "max" : 0,
          "mean" : 0.000000,
          "stddev" : 0.000000,
          "N" : 0
        },
        "clat_ns" : {
          "min" : 3180020,
          "max" : 5116117,
          "mean" : 4596753.359375,
          "stddev" : 143808.672243,
          "N" : 256,
          "percentile" : {
            "1.000000" : 3817472,
            "5.000000" : 4554752,
            "10.000000" : 4554752,
            "20.000000" : 4554752,
            "30.000000" : 4554752,
            "40.000000" : 4554752,
            "50.000000" : 4554752,
            "60.000000" : 4554752,
            "70.000000" : 4620288,
            "80.000000" : 4620288,
            "90.000000" : 4685824,
            "95.000000" : 4751360,
            "99.000000" : 4882432,
            "99.500000" : 4947968,
            "99.900000" : 5144576,
            "99.950000" : 5144576,
            "99.990000" : 5144576
          }
        },
        "lat_ns" : {
          "min" : 3208682,
          "max" : 5138714,
          "mean" : 4628803.769531,
          "stddev" : 144916.425721,
          "N" : 256
        },
        "bw_min" : 438272,
        "bw_max" : 442368,
        "bw_agg" : 43.125977,
        "bw_mean" : 440320.000000,
        "bw_dev" : 2896.309376,
        "bw_samples" : 2,
        "iops_min" : 214,
        "iops_max" : 216,
        "iops_mean" : 215.000000,
        "iops_stddev" : 1.414214,
        "iops_samples" : 2
      },
      "trim" : {
        "io_bytes" : 0,
        "io_kbytes" : 0,
        "bw_bytes" : 0,
        "bw" : 0,
        "iops" : 0.000000,
        "runtime" : 0,
        "total_ios" : 0,
        "short_ios" : 0,
        "drop_ios" : 0,
        "slat_ns" : {
          "min" : 0,
          "max" : 0,
          "mean" : 0.000000,
          "stddev" : 0.000000,
          "N" : 0
        },
        "clat_ns" : {
          "min" : 0,
          "max" : 0,
          "mean" : 0.000000,
          "stddev" : 0.000000,
          "N" : 0
        },
        "lat_ns" : {
          "min" : 0,
          "max" : 0,
          "mean" : 0.000000,
          "stddev" : 0.000000,
          "N" : 0
        },
        "bw_min" : 0,
        "bw_max" : 0,
        "bw_agg" : 0.000000,
        "bw_mean" : 0.000000,
        "bw_dev" : 0.000000,
        "bw_samples" : 0,
        "iops_min" : 0,
        "iops_max" : 0,
        "iops_mean" : 0.000000,
        "iops_stddev" : 0.000000,
        "iops_samples" : 0
      },
      "sync" : {
        "total_ios" : 0,
        "lat_ns" : {
          "min" : 0,
          "max" : 0,
          "mean" : 0.000000,
          "stddev" : 0.000000,
          "N" : 0
        }
      },
      "job_runtime" : 1185,
      "usr_cpu" : 1.772152,
      "sys_cpu" : 0.000000,
      "ctx" : 256,
      "majf" : 0,
      "minf" : 9,
      "iodepth_level" : {
        "1" : 100.000000,
        "2" : 0.000000,
        "4" : 0.000000,
        "8" : 0.000000,
        "16" : 0.000000,
        "32" : 0.000000,
        ">=64" : 0.000000
      },
      "iodepth_submit" : {
        "0" : 0.000000,
        "4" : 100.000000,
        "8" : 0.000000,
        "16" : 0.000000,
        "32" : 0.000000,
        "64" : 0.000000,
        ">=64" : 0.000000
      },
      "iodepth_complete" : {
        "0" : 0.000000,
        "4" : 100.000000,
        "8" : 0.000000,
        "16" : 0.000000,
        "32" : 0.000000,
        "64" : 0.000000,
        ">=64" : 0.000000
      },
      "latency_ns" : {
        "2" : 0.000000,
        "4" : 0.000000,
        "10" : 0.000000,
        "20" : 0.000000,
        "50" : 0.000000,
        "100" : 0.000000,
        "250" : 0.000000,
        "500" : 0.000000,
        "750" : 0.000000,
        "1000" : 0.000000
      },
      "latency_us" : {
        "2" : 0.000000,
        "4" : 0.000000,
        "10" : 0.000000,
        "20" : 0.000000,
        "50" : 0.000000,
        "100" : 0.000000,
        "250" : 0.000000,
        "500" : 0.000000,
        "750" : 0.000000,
        "1000" : 0.000000
      },
      "latency_ms" : {
        "2" : 0.000000,
        "4" : 1.562500,
        "10" : 98.437500,
        "20" : 0.000000,
        "50" : 0.000000,
        "100" : 0.000000,
        "250" : 0.000000,
        "500" : 0.000000,
        "750" : 0.000000,
        "1000" : 0.000000,
        "2000" : 0.000000,
        ">=2000" : 0.000000
      },
      "latency_depth" : 1,
      "latency_target" : 0,
      "latency_percentile" : 100.000000,
      "latency_window" : 0
    },
    {
      "jobname" : "zone4_write",
      "groupid" : 0,
      "error" : 0,
      "eta" : 0,
      "elapsed" : 4,
      "job options" : {
        "ioengine" : "psync",
        "bs" : "2m",
        "rw" : "write",
        "offset" : "4z"
      },
      "read" : {
        "io_bytes" : 0,
        "io_kbytes" : 0,
        "bw_bytes" : 0,
        "bw" : 0,
        "iops" : 0.000000,
        "runtime" : 0,
        "total_ios" : 0,
        "short_ios" : 0,
        "drop_ios" : 0,
        "slat_ns" : {
          "min" : 0,
          "max" : 0,
          "mean" : 0.000000,
          "stddev" : 0.000000,
          "N" : 0
        },
        "clat_ns" : {
          "min" : 0,
          "max" : 0,
          "mean" : 0.000000,
          "stddev" : 0.000000,
          "N" : 0
        },
        "lat_ns" : {
          "min" : 0,
          "max" : 0,
          "mean" : 0.000000,
          "stddev" : 0.000000,
          "N" : 0
        },
        "bw_min" : 0,
        "bw_max" : 0,
        "bw_agg" : 0.000000,
        "bw_mean" : 0.000000,
        "bw_dev" : 0.000000,
        "bw_samples" : 0,
        "iops_min" : 0,
        "iops_max" : 0,
        "iops_mean" : 0.000000,
        "iops_stddev" : 0.000000,
        "iops_samples" : 0
      },
      "write" : {
        "io_bytes" : 536870912,
        "io_kbytes" : 524288,
        "bw_bytes" : 489845722,
        "bw" : 478364,
        "iops" : 233.576642,
        "runtime" : 1096,
        "total_ios" : 256,
        "short_ios" : 0,
        "drop_ios" : 0,
        "slat_ns" : {
          "min" : 0,
          "max" : 0,
          "mean" : 0.000000,
          "stddev" : 0.000000,
          "N" : 0
        },
        "clat_ns" : {
          "min" : 3811487,
          "max" : 6503111,
          "mean" : 4250096.789062,
          "stddev" : 369811.036403,
          "N" : 256,
          "percentile" : {
            "1.000000" : 3850240,
            "5.000000" : 4112384,
            "10.000000" : 4112384,
            "20.000000" : 4112384,
            "30.000000" : 4112384,
            "40.000000" : 4145152,
            "50.000000" : 4145152,
            "60.000000" : 4145152,
            "70.000000" : 4145152,
            "80.000000" : 4227072,
            "90.000000" : 4423680,
            "95.000000" : 5406720,
            "99.000000" : 5734400,
            "99.500000" : 5734400,
            "99.900000" : 6520832,
            "99.950000" : 6520832,
            "99.990000" : 6520832
          }
        },
        "lat_ns" : {
          "min" : 3833050,
          "max" : 6533958,
          "mean" : 4279499.078125,
          "stddev" : 372108.481498,
          "N" : 256
        },
        "bw_min" : 471040,
        "bw_max" : 483328,
        "bw_agg" : 46.736523,
        "bw_mean" : 477184.000000,
        "bw_dev" : 8688.928127,
        "bw_samples" : 2,
        "iops_min" : 230,
        "iops_max" : 236,
        "iops_mean" : 233.000000,
        "iops_stddev" : 4.242641,
        "iops_samples" : 2
      },
      "trim" : {
        "io_bytes" : 0,
        "io_kbytes" : 0,
        "bw_bytes" : 0,
        "bw" : 0,
        "iops" : 0.000000,
        "runtime" : 0,
        "total_ios" : 0,
        "short_ios" : 0,
        "drop_ios" : 0,
        "slat_ns" : {
          "min" : 0,
          "max" : 0,
          "mean" : 0.000000,
          "stddev" : 0.000000,
          "N" : 0
        },
        "clat_ns" : {
          "min" : 0,
          "max" : 0,
          "mean" : 0.000000,
          "stddev" : 0.000000,
          "N" : 0
        },
        "lat_ns" : {
          "min" : 0,
          "max" : 0,
          "mean" : 0.000000,
          "stddev" : 0.000000,
          "N" : 0
        },
        "bw_min" : 0,
        "bw_max" : 0,
        "bw_agg" : 0.000000,
        "bw_mean" : 0.000000,
        "bw_dev" : 0.000000,
        "bw_samples" : 0,
        "iops_min" : 0,
        "iops_max" : 0,
        "iops_mean" : 0.000000,
        "iops_stddev" : 0.000000,
        "iops_samples" : 0
      },
      "sync" : {
        "total_ios" : 0,
        "lat_ns" : {
          "min" : 0,
          "max" : 0,
          "mean" : 0.000000,
          "stddev" : 0.000000,
          "N" : 0
        }
      },
      "job_runtime" : 1095,
      "usr_cpu" : 0.913242,
      "sys_cpu" : 0.913242,
      "ctx" : 257,
      "majf" : 0,
      "minf" : 12,
      "iodepth_level" : {
        "1" : 100.000000,
        "2" : 0.000000,
        "4" : 0.000000,
        "8" : 0.000000,
        "16" : 0.000000,
        "32" : 0.000000,
        ">=64" : 0.000000
      },
      "iodepth_submit" : {
        "0" : 0.000000,
        "4" : 100.000000,
        "8" : 0.000000,
        "16" : 0.000000,
        "32" : 0.000000,
        "64" : 0.000000,
        ">=64" : 0.000000
      },
      "iodepth_complete" : {
        "0" : 0.000000,
        "4" : 100.000000,
        "8" : 0.000000,
        "16" : 0.000000,
        "32" : 0.000000,
        "64" : 0.000000,
        ">=64" : 0.000000
      },
      "latency_ns" : {
        "2" : 0.000000,
        "4" : 0.000000,
        "10" : 0.000000,
        "20" : 0.000000,
        "50" : 0.000000,
        "100" : 0.000000,
        "250" : 0.000000,
        "500" : 0.000000,
        "750" : 0.000000,
        "1000" : 0.000000
      },
      "latency_us" : {
        "2" : 0.000000,
        "4" : 0.000000,
        "10" : 0.000000,
        "20" : 0.000000,
        "50" : 0.000000,
        "100" : 0.000000,
        "250" : 0.000000,
        "500" : 0.000000,
        "750" : 0.000000,
        "1000" : 0.000000
      },
      "latency_ms" : {
        "2" : 0.000000,
        "4" : 1.171875,
        "10" : 98.828125,
        "20" : 0.000000,
        "50" : 0.000000,
        "100" : 0.000000,
        "250" : 0.000000,
        "500" : 0.000000,
        "750" : 0.000000,
        "1000" : 0.000000,
        "2000" : 0.000000,
        ">=2000" : 0.000000
      },
      "latency_depth" : 1,
      "latency_target" : 0,
      "latency_percentile" : 100.000000,
      "latency_window" : 0
    },
    {
      "jobname" : "zone8_write",
      "groupid" : 0,
      "error" : 0,
      "eta" : 0,
      "elapsed" : 4,
      "job options" : {
        "ioengine" : "psync",
        "bs" : "2m",
        "rw" : "write",
        "offset" : "8z"
      },
      "read" : {
        "io_bytes" : 0,
        "io_kbytes" : 0,
        "bw_bytes" : 0,
        "bw" : 0,
        "iops" : 0.000000,
        "runtime" : 0,
        "total_ios" : 0,
        "short_ios" : 0,
        "drop_ios" : 0,
        "slat_ns" : {
          "min" : 0,
          "max" : 0,
          "mean" : 0.000000,
          "stddev" : 0.000000,
          "N" : 0
        },
        "clat_ns" : {
          "min" : 0,
          "max" : 0,
          "mean" : 0.000000,
          "stddev" : 0.000000,
          "N" : 0
        },
        "lat_ns" : {
          "min" : 0,
          "max" : 0,
          "mean" : 0.000000,
          "stddev" : 0.000000,
          "N" : 0
        },
        "bw_min" : 0,
        "bw_max" : 0,
        "bw_agg" : 0.000000,
        "bw_mean" : 0.000000,
        "bw_dev" : 0.000000,
        "bw_samples" : 0,
        "iops_min" : 0,
        "iops_max" : 0,
        "iops_mean" : 0.000000,
        "iops_stddev" : 0.000000,
        "iops_samples" : 0
      },
      "write" : {
        "io_bytes" : 536870912,
        "io_kbytes" : 524288,
        "bw_bytes" : 174365349,
        "bw" : 170278,
        "iops" : 83.143878,
        "runtime" : 3079,
        "total_ios" : 256,
        "short_ios" : 0,
        "drop_ios" : 0,
        "slat_ns" : {
          "min" : 0,
          "max" : 0,
          "mean" : 0.000000,
          "stddev" : 0.000000,
          "N" : 0
        },
        "clat_ns" : {
          "min" : 5781309,
          "max" : 12383810,
          "mean" : 11979693.019531,
          "stddev" : 617917.492805,
          "N" : 256,
          "percentile" : {
            "1.000000" : 8355840,
            "5.000000" : 11993088,
            "10.000000" : 11993088,
            "20.000000" : 11993088,
            "30.000000" : 11993088,
            "40.000000" : 11993088,
            "50.000000" : 12124160,
            "60.000000" : 12124160,
            "70.000000" : 12124160,
            "80.000000" : 12124160,
            "90.000000" : 12124160,
            "95.000000" : 12124160,
            "99.000000" : 12255232,
            "99.500000" : 12255232,
            "99.900000" : 12386304,
            "99.950000" : 12386304,
            "99.990000" : 12386304
          }
        },
        "lat_ns" : {
          "min" : 5804149,
          "max" : 12435449,
          "mean" : 12023258.691406,
          "stddev" : 620692.110560,
          "N" : 256
        },
        "bw_min" : 167936,
        "bw_max" : 172032,
        "bw_agg" : 16.581738,
        "bw_mean" : 169301.333333,
        "bw_dev" : 2115.165305,
        "bw_samples" : 6,
        "iops_min" : 82,
        "iops_max" : 84,
        "iops_mean" : 82.666667,
        "iops_stddev" : 1.032796,
        "iops_samples" : 6
      },
      "trim" : {
        "io_bytes" : 0,
        "io_kbytes" : 0,
        "bw_bytes" : 0,
        "bw" : 0,
        "iops" : 0.000000,
        "runtime" : 0,
        "total_ios" : 0,
        "short_ios" : 0,
        "drop_ios" : 0,
        "slat_ns" : {
          "min" : 0,
          "max" : 0,
          "mean" : 0.000000,
          "stddev" : 0.000000,
          "N" : 0
        },
        "clat_ns" : {
          "min" : 0,
          "max" : 0,
          "mean" : 0.000000,
          "stddev" : 0.000000,
          "N" : 0
        },
        "lat_ns" : {
          "min" : 0,
          "max" : 0,
          "mean" : 0.000000,
          "stddev" : 0.000000,
          "N" : 0
        },
        "bw_min" : 0,
        "bw_max" : 0,
        "bw_agg" : 0.000000,
        "bw_mean" : 0.000000,
        "bw_dev" : 0.000000,
        "bw_samples" : 0,
        "iops_min" : 0,
        "iops_max" : 0,
        "iops_mean" : 0.000000,
        "iops_stddev" : 0.000000,
        "iops_samples" : 0
      },
      "sync" : {
        "total_ios" : 0,
        "lat_ns" : {
          "min" : 0,
          "max" : 0,
          "mean" : 0.000000,
          "stddev" : 0.000000,
          "N" : 0
        }
      },
      "job_runtime" : 3078,
      "usr_cpu" : 0.747238,
      "sys_cpu" : 0.097466,
      "ctx" : 257,
      "majf" : 0,
      "minf" : 11,
      "iodepth_level" : {
        "1" : 100.000000,
        "2" : 0.000000,
        "4" : 0.000000,
        "8" : 0.000000,
        "16" : 0.000000,
        "32" : 0.000000,
        ">=64" : 0.000000
      },
      "iodepth_submit" : {
        "0" : 0.000000,
        "4" : 100.000000,
        "8" : 0.000000,
        "16" : 0.000000,
        "32" : 0.000000,
        "64" : 0.000000,
        ">=64" : 0.000000
      },
      "iodepth_complete" : {
        "0" : 0.000000,
        "4" : 100.000000,
        "8" : 0.000000,
        "16" : 0.000000,
        "32" : 0.000000,
        "64" : 0.000000,
        ">=64" : 0.000000
      },
      "latency_ns" : {
        "2" : 0.000000,
        "4" : 0.000000,
        "10" : 0.000000,
        "20" : 0.000000,
        "50" : 0.000000,
        "100" : 0.000000,
        "250" : 0.000000,
        "500" : 0.000000,
        "750" : 0.000000,
        "1000" : 0.000000
      },
      "latency_us" : {
        "2" : 0.000000,
        "4" : 0.000000,
        "10" : 0.000000,
        "20" : 0.000000,
        "50" : 0.000000,
        "100" : 0.000000,
        "250" : 0.000000,
        "500" : 0.000000,
        "750" : 0.000000,
        "1000" : 0.000000
      },
      "latency_ms" : {
        "2" : 0.000000,
        "4" : 0.000000,
        "10" : 1.953125,
        "20" : 98.046875,
        "50" : 0.000000,
        "100" : 0.000000,
        "250" : 0.000000,
        "500" : 0.000000,
        "750" : 0.000000,
        "1000" : 0.000000,
        "2000" : 0.000000,
        ">=2000" : 0.000000
      },
      "latency_depth" : 1,
      "latency_target" : 0,
      "latency_percentile" : 100.000000,
      "latency_window" : 0
    },
    {
      "jobname" : "zone16_write",
      "groupid" : 0,
      "error" : 0,
      "eta" : 0,
      "elapsed" : 4,
      "job options" : {
        "ioengine" : "psync",
        "bs" : "2m",
        "rw" : "write",
        "offset" : "16z"
      },
      "read" : {
        "io_bytes" : 0,
        "io_kbytes" : 0,
        "bw_bytes" : 0,
        "bw" : 0,
        "iops" : 0.000000,
        "runtime" : 0,
        "total_ios" : 0,
        "short_ios" : 0,
        "drop_ios" : 0,
        "slat_ns" : {
          "min" : 0,
          "max" : 0,
          "mean" : 0.000000,
          "stddev" : 0.000000,
          "N" : 0
        },
        "clat_ns" : {
          "min" : 0,
          "max" : 0,
          "mean" : 0.000000,
          "stddev" : 0.000000,
          "N" : 0
        },
        "lat_ns" : {
          "min" : 0,
          "max" : 0,
          "mean" : 0.000000,
          "stddev" : 0.000000,
          "N" : 0
        },
        "bw_min" : 0,
        "bw_max" : 0,
        "bw_agg" : 0.000000,
        "bw_mean" : 0.000000,
        "bw_dev" : 0.000000,
        "bw_samples" : 0,
        "iops_min" : 0,
        "iops_max" : 0,
        "iops_mean" : 0.000000,
        "iops_stddev" : 0.000000,
        "iops_samples" : 0
      },
      "write" : {
        "io_bytes" : 536870912,
        "io_kbytes" : 524288,
        "bw_bytes" : 174252162,
        "bw" : 170168,
        "iops" : 83.089906,
        "runtime" : 3081,
        "total_ios" : 256,
        "short_ios" : 0,
        "drop_ios" : 0,
        "slat_ns" : {
          "min" : 0,
          "max" : 0,
          "mean" : 0.000000,
          "stddev" : 0.000000,
          "N" : 0
        },
        "clat_ns" : {
          "min" : 5799562,
          "max" : 12455444,
          "mean" : 11988179.464844,
          "stddev" : 600024.949869,
          "N" : 256,
          "percentile" : {
            "1.000000" : 8978432,
            "5.000000" : 11993088,
            "10.000000" : 11993088,
            "20.000000" : 11993088,
            "30.000000" : 11993088,
            "40.000000" : 11993088,
            "50.000000" : 12124160,
            "60.000000" : 12124160,
            "70.000000" : 12124160,
            "80.000000" : 12124160,
            "90.000000" : 12124160,
            "95.000000" : 12124160,
            "99.000000" : 12386304,
            "99.500000" : 12386304,
            "99.900000" : 12517376,
            "99.950000" : 12517376,
            "99.990000" : 12517376
          }
        },
        "lat_ns" : {
          "min" : 5831645,
          "max" : 12506780,
          "mean" : 12030784.417969,
          "stddev" : 601830.416333,
          "N" : 256
        },
        "bw_min" : 167936,
        "bw_max" : 172032,
        "bw_agg" : 16.520328,
        "bw_mean" : 168674.666667,
        "bw_dev" : 1650.232792,
        "bw_samples" : 6,
        "iops_min" : 82,
        "iops_max" : 84,
        "iops_mean" : 82.333333,
        "iops_stddev" : 0.816497,
        "iops_samples" : 6
      },
      "trim" : {
        "io_bytes" : 0,
        "io_kbytes" : 0,
        "bw_bytes" : 0,
        "bw" : 0,
        "iops" : 0.000000,
        "runtime" : 0,
        "total_ios" : 0,
        "short_ios" : 0,
        "drop_ios" : 0,
        "slat_ns" : {
          "min" : 0,
          "max" : 0,
          "mean" : 0.000000,
          "stddev" : 0.000000,
          "N" : 0
        },
        "clat_ns" : {
          "min" : 0,
          "max" : 0,
          "mean" : 0.000000,
          "stddev" : 0.000000,
          "N" : 0
        },
        "lat_ns" : {
          "min" : 0,
          "max" : 0,
          "mean" : 0.000000,
          "stddev" : 0.000000,
          "N" : 0
        },
        "bw_min" : 0,
        "bw_max" : 0,
        "bw_agg" : 0.000000,
        "bw_mean" : 0.000000,
        "bw_dev" : 0.000000,
        "bw_samples" : 0,
        "iops_min" : 0,
        "iops_max" : 0,
        "iops_mean" : 0.000000,
        "iops_stddev" : 0.000000,
        "iops_samples" : 0
      },
      "sync" : {
        "total_ios" : 0,
        "lat_ns" : {
          "min" : 0,
          "max" : 0,
          "mean" : 0.000000,
          "stddev" : 0.000000,
          "N" : 0
        }
      },
      "job_runtime" : 3080,
      "usr_cpu" : 0.584416,
      "sys_cpu" : 0.292208,
      "ctx" : 256,
      "majf" : 0,
      "minf" : 11,
      "iodepth_level" : {
        "1" : 100.000000,
        "2" : 0.000000,
        "4" : 0.000000,
        "8" : 0.000000,
        "16" : 0.000000,
        "32" : 0.000000,
        ">=64" : 0.000000
      },
      "iodepth_submit" : {
        "0" : 0.000000,
        "4" : 100.000000,
        "8" : 0.000000,
        "16" : 0.000000,
        "32" : 0.000000,
        "64" : 0.000000,
        ">=64" : 0.000000
      },
      "iodepth_complete" : {
        "0" : 0.000000,
        "4" : 100.000000,
        "8" : 0.000000,
        "16" : 0.000000,
        "32" : 0.000000,
        "64" : 0.000000,
        ">=64" : 0.000000
      },
      "latency_ns" : {
        "2" : 0.000000,
        "4" : 0.000000,
        "10" : 0.000000,
        "20" : 0.000000,
        "50" : 0.000000,
        "100" : 0.000000,
        "250" : 0.000000,
        "500" : 0.000000,
        "750" : 0.000000,
        "1000" : 0.000000
      },
      "latency_us" : {
        "2" : 0.000000,
        "4" : 0.000000,
        "10" : 0.000000,
        "20" : 0.000000,
        "50" : 0.000000,
        "100" : 0.000000,
        "250" : 0.000000,
        "500" : 0.000000,
        "750" : 0.000000,
        "1000" : 0.000000
      },
      "latency_ms" : {
        "2" : 0.000000,
        "4" : 0.000000,
        "10" : 1.562500,
        "20" : 98.437500,
        "50" : 0.000000,
        "100" : 0.000000,
        "250" : 0.000000,
        "500" : 0.000000,
        "750" : 0.000000,
        "1000" : 0.000000,
        "2000" : 0.000000,
        ">=2000" : 0.000000
      },
      "latency_depth" : 1,
      "latency_target" : 0,
      "latency_percentile" : 100.000000,
      "latency_window" : 0
    }
  ],
  "disk_util" : [
    {
      "name" : "nvme0n1",
      "read_ios" : 147,
      "write_ios" : 7667,
      "read_merges" : 0,
      "write_merges" : 0,
      "read_ticks" : 201,
      "write_ticks" : 48986,
      "in_queue" : 49188,
      "util" : 97.297297
    }
  ]
}
